myFbase/__init__.py
myFbase/myfbase.py
myFbase-0.1.1.dist-info/LICENSE
myFbase-0.1.1.dist-info/WHEEL
myFbase-0.1.1.dist-info/METADATA
myFbase-0.1.1.dist-info/RECORD
