Metadata-Version: 2.1
Name: myFbase
Version: 0.1.1
Summary: Change to/from any base you like
Home-page: https://github.com/victor141516/myFbase
License: UNKNOWN
Author: victor141516
Author-email: yomellamovictor@gmail.com
Classifier: License :: OSI Approved :: MIT License
